prospector_profile_duplicated/__init__.py
prospector_profile_duplicated/black.yaml
prospector_profile_duplicated/docformatter.yaml
prospector_profile_duplicated/isort.yaml
prospector_profile_duplicated/prospector.yaml
prospector_profile_duplicated/pydocstyle.yaml
prospector_profile_duplicated/pyupgrade.yaml
prospector_profile_duplicated/ruff.yaml
prospector_profile_duplicated-1.11.0.dist-info/LICENSE
prospector_profile_duplicated-1.11.0.dist-info/METADATA
prospector_profile_duplicated-1.11.0.dist-info/WHEEL
prospector_profile_duplicated-1.11.0.dist-info/RECORD
