Metadata-Version: 2.3
Name: prospector-profile-duplicated
Version: 1.11.0
Summary: Profile that can be used to disable the duplicated or conflict rules between Prospector and other tools
License: BSD-2-Clause
Author: Stéphane Brunner
Author-email: stephane.brunner@gmail.com
Classifier: Development Status :: 5 - Production/Stable
Classifier: Intended Audience :: Developers
Classifier: License :: OSI Approved :: BSD License
Classifier: Operating System :: OS Independent
Classifier: Programming Language :: Python
Classifier: Programming Language :: Python :: 3
Requires-Dist: prospector
Project-URL: Bug Tracker, https://github.com/sbrunner/prospector-profile-duplicated/issues
Project-URL: Repository, https://github.com/sbrunner/prospector-profile-duplicated
